{
  "pluginId": "default",
  "version": "current",
  "label": "Next",
  "banner": null,
  "badge": false,
  "className": "docs-version-current",
  "isLast": true,
  "docsSidebars": {
    "tutorialSidebar": [
      {
        "type": "link",
        "label": "Blox Architecture",
        "href": "/docs/intro",
        "docId": "intro"
      },
      {
        "type": "link",
        "label": "Composability vs Dependency",
        "href": "/docs/composability-vs-dependency",
        "docId": "composability-vs-dependency"
      },
      {
        "type": "link",
        "label": "Types of Blox",
        "href": "/docs/types-of-blox",
        "docId": "types-of-blox"
      },
      {
        "type": "category",
        "label": "Blox CLI",
        "collapsible": true,
        "collapsed": true,
        "items": [
          {
            "type": "category",
            "label": "Commands",
            "collapsible": true,
            "collapsed": true,
            "items": [
              {
                "type": "link",
                "label": "blox login",
                "href": "/docs/blox-cli/Commands/blox-login",
                "docId": "blox-cli/Commands/blox-login"
              },
              {
                "type": "link",
                "label": "blox connect",
                "href": "/docs/blox-cli/Commands/blox-connect",
                "docId": "blox-cli/Commands/blox-connect"
              },
              {
                "type": "link",
                "label": "blox start",
                "href": "/docs/blox-cli/Commands/blox-start",
                "docId": "blox-cli/Commands/blox-start"
              },
              {
                "type": "link",
                "label": "blox stop",
                "href": "/docs/blox-cli/Commands/blox-stop",
                "docId": "blox-cli/Commands/blox-stop"
              },
              {
                "type": "link",
                "label": "Blox Init",
                "href": "/docs/blox-cli/Commands/blox-init",
                "docId": "blox-cli/Commands/blox-init"
              },
              {
                "type": "link",
                "label": "blox create",
                "href": "/docs/blox-cli/Commands/blox-create",
                "docId": "blox-cli/Commands/blox-create"
              },
              {
                "type": "link",
                "label": "blox log",
                "href": "/docs/blox-cli/Commands/blox-log",
                "docId": "blox-cli/Commands/blox-log"
              },
              {
                "type": "link",
                "label": "blox push",
                "href": "/docs/blox-cli/Commands/blox-push",
                "docId": "blox-cli/Commands/blox-push"
              },
              {
                "type": "link",
                "label": "blox push-config",
                "href": "/docs/blox-cli/Commands/blox-push-config",
                "docId": "blox-cli/Commands/blox-push-config"
              },
              {
                "type": "link",
                "label": "blox exec",
                "href": "/docs/blox-cli/Commands/blox-exec",
                "docId": "blox-cli/Commands/blox-exec"
              },
              {
                "type": "link",
                "label": "blox ls",
                "href": "/docs/blox-cli/Commands/blox-ls",
                "docId": "blox-cli/Commands/blox-ls"
              },
              {
                "type": "link",
                "label": "blox sync",
                "href": "/docs/blox-cli/Commands/blox-sync",
                "docId": "blox-cli/Commands/blox-sync"
              },
              {
                "type": "link",
                "label": "blox pull",
                "href": "/docs/blox-cli/Commands/blox-pull",
                "docId": "blox-cli/Commands/blox-pull"
              }
            ]
          }
        ]
      },
      {
        "type": "category",
        "label": "Blox SDK",
        "collapsible": true,
        "collapsed": true,
        "items": [
          {
            "type": "link",
            "label": "Blox JS SDK",
            "href": "/docs/blox-sdk/blox-js-sdk",
            "docId": "blox-sdk/blox-js-sdk"
          },
          {
            "type": "link",
            "label": "Node blox SDK",
            "href": "/docs/blox-sdk/blox-nodejs-sdk",
            "docId": "blox-sdk/blox-nodejs-sdk"
          }
        ]
      },
      {
        "type": "category",
        "label": "Blox Store",
        "collapsible": true,
        "collapsed": true,
        "items": [
          {
            "type": "link",
            "label": "Blox Store Walkthrough",
            "href": "/docs/blox-store/walkthrough",
            "docId": "blox-store/walkthrough"
          }
        ]
      }
    ]
  },
  "docs": {
    "blox-cli/Commands/blox-connect": {
      "id": "blox-cli/Commands/blox-connect",
      "title": "blox connect",
      "description": "To connect to Github.",
      "sidebar": "tutorialSidebar"
    },
    "blox-cli/Commands/blox-create": {
      "id": "blox-cli/Commands/blox-create",
      "title": "blox create",
      "description": "Blox create can be used to create all kinds of bloxes!",
      "sidebar": "tutorialSidebar"
    },
    "blox-cli/Commands/blox-exec": {
      "id": "blox-cli/Commands/blox-exec",
      "title": "blox exec",
      "description": "Blox exec lets you run system commands inside all Blox directories in one go.",
      "sidebar": "tutorialSidebar"
    },
    "blox-cli/Commands/blox-init": {
      "id": "blox-cli/Commands/blox-init",
      "title": "Blox Init",
      "description": "Blox init command can be employed to create and register an appblox.",
      "sidebar": "tutorialSidebar"
    },
    "blox-cli/Commands/blox-log": {
      "id": "blox-cli/Commands/blox-log",
      "title": "blox log",
      "description": "Blox log command reads and displays logs related to live bloxes.",
      "sidebar": "tutorialSidebar"
    },
    "blox-cli/Commands/blox-login": {
      "id": "blox-cli/Commands/blox-login",
      "title": "blox login",
      "description": "blox login lets you log into Appblox/ Blox Registry.",
      "sidebar": "tutorialSidebar"
    },
    "blox-cli/Commands/blox-ls": {
      "id": "blox-cli/Commands/blox-ls",
      "title": "blox ls",
      "description": "To display the Blox and its current statuses.",
      "sidebar": "tutorialSidebar"
    },
    "blox-cli/Commands/blox-pull": {
      "id": "blox-cli/Commands/blox-pull",
      "title": "blox pull",
      "description": "Pull command is used pull new bloxes into an app.",
      "sidebar": "tutorialSidebar"
    },
    "blox-cli/Commands/blox-push": {
      "id": "blox-cli/Commands/blox-push",
      "title": "blox push",
      "description": "To push Blox code to source control.",
      "sidebar": "tutorialSidebar"
    },
    "blox-cli/Commands/blox-push-config": {
      "id": "blox-cli/Commands/blox-push-config",
      "title": "blox push-config",
      "description": "To push the AppBlox config to registry.",
      "sidebar": "tutorialSidebar"
    },
    "blox-cli/Commands/blox-start": {
      "id": "blox-cli/Commands/blox-start",
      "title": "blox start",
      "description": "1. Start all bloxes",
      "sidebar": "tutorialSidebar"
    },
    "blox-cli/Commands/blox-stop": {
      "id": "blox-cli/Commands/blox-stop",
      "title": "blox stop",
      "description": "Blox stop will stop all running ui bloxes and also kill the emulator",
      "sidebar": "tutorialSidebar"
    },
    "blox-cli/Commands/blox-sync": {
      "id": "blox-cli/Commands/blox-sync",
      "title": "blox sync",
      "description": "Blox sync command can be used to convert existing projects that were not built as bloxes, to appblox projects.",
      "sidebar": "tutorialSidebar"
    },
    "blox-sdk/blox-js-sdk": {
      "id": "blox-sdk/blox-js-sdk",
      "title": "Blox JS SDK",
      "description": "blox-js-sdk provides the essential packages to facilitate appblox features across appblox applications.",
      "sidebar": "tutorialSidebar"
    },
    "blox-sdk/blox-nodejs-sdk": {
      "id": "blox-sdk/blox-nodejs-sdk",
      "title": "Node blox SDK",
      "description": "The Node Blox SDK implements the server-side libraries used by applications using Appblox services.",
      "sidebar": "tutorialSidebar"
    },
    "blox-store/walkthrough": {
      "id": "blox-store/walkthrough",
      "title": "Blox Store Walkthrough",
      "description": "Blox Store",
      "sidebar": "tutorialSidebar"
    },
    "composability-vs-dependency": {
      "id": "composability-vs-dependency",
      "title": "Composability vs Dependency",
      "description": "Composability",
      "sidebar": "tutorialSidebar"
    },
    "intro": {
      "id": "intro",
      "title": "Blox Architecture",
      "description": "“As business needs change, organizations must be able to deliver innovation quickly and adapt applications dynamically — reassembling capabilities from inside and outside the enterprise. To do this, organizations must understand and implement the “composable enterprise.” – Gartner",
      "sidebar": "tutorialSidebar"
    },
    "types-of-blox": {
      "id": "types-of-blox",
      "title": "Types of Blox",
      "description": "We have predefined types for Blox in the registry. Each type refers to where and how it is utilised. Following is the list of Blox Types available.",
      "sidebar": "tutorialSidebar"
    }
  }
}